{
  "title": "PERISAI BPJS KETENAGAKERJAAN",
  "subTitle": null,
  "description": null,
  "price": null,
  "categoryName": "Asosiasi/organisasi",
  "address": "R9RQ+7M8, KP.GEMPOL DAMPIT, RT.003/RW.003, Koper, Kec. Cikande, Kabupaten Serang, Banten 42186, Indonesia",
  "neighborhood": "Koper, Kecamatan Cikande",
  "street": "R9RQ+7M8, KP.GEMPOL DAMPIT, RT.003/RW.003",
  "city": "Kabupaten Serang",
  "postalCode": "42186",
  "state": "Banten",
  "countryCode": "ID",
  "phone": "",
  "phoneUnformatted": "",
  "claimThisBusiness": true,
  "location": {
    "lat": -6.159327,
    "lng": 106.3891982
  },
  "locatedIn": null,
  "floor": null,
  "plusCode": null,
  "menu": null,
  "servicesLink": null,
  "totalScore": 4.8,
  "permanentlyClosed": false,
  "temporarilyClosed": false,
  "placeId": "ChIJUWvBUVEDQi4RtPkgdrxFDJY",
  "categories": [
    "Asosiasi/organisasi"
  ],
  "fid": "0x2e42035151c16b51:0x960c45bc7620f9b4",
  "cid": "10812093481147759028",
  "reviewsCount": 6,
  "reviewsDistribution": {
    "oneStar": 0,
    "twoStar": 0,
    "threeStar": 0,
    "fourStar": 1,
    "fiveStar": 5
  },
  "imagesCount": 8,
  "imageCategories": [
    "Semua",
    "Street View & 360°"
  ],
  "scrapedAt": "2026-07-22T10:23:24.181Z",
  "reserveTableUrl": null,
  "googleFoodUrl": null,
  "hotelStars": null,
  "hotelDescription": null,
  "checkInDate": null,
  "checkOutDate": null,
  "hotelAds": [],
  "popularTimesLiveText": null,
  "popularTimesLivePercent": null,
  "popularTimesHistogram": {},
  "openingHours": [
    {
      "day": "Rabu",
      "hours": "Buka 24 jAM"
    },
    {
      "day": "Kamis",
      "hours": "Buka 24 jAM"
    },
    {
      "day": "Jumat",
      "hours": "Buka 24 jAM"
    },
    {
      "day": "Sabtu",
      "hours": "Buka 24 jAM"
    },
    {
      "day": "Minggu",
      "hours": "Buka 24 jAM"
    },
    {
      "day": "Senin",
      "hours": "Buka 24 jAM"
    },
    {
      "day": "Selasa",
      "hours": "Buka 24 jAM"
    }
  ],
  "peopleAlsoSearch": [
    {
      "category": "Orang lain juga menelusuri",
      "title": "BPJS KETENAGAKERJAAN (Agen Perisai)",
      "reviewsCount": 3,
      "totalScore": 5
    },
    {
      "category": "Orang lain juga menelusuri",
      "title": "Kantor Perisai BPJS Ketenagakerjaan Lebak",
      "reviewsCount": 2,
      "totalScore": 5
    },
    {
      "category": "Orang lain juga menelusuri",
      "title": "Jasa Pencairan BPJS Ketenagakerjaan & JAMSOSTEK",
      "reviewsCount": 5,
      "totalScore": 4.2
    },
    {
      "category": "Orang lain juga menelusuri",
      "title": "BPJS Ketenagakerjaan Tangerang Cimone",
      "reviewsCount": 518,
      "totalScore": 4.2
    }
  ],
  "placesTags": [
    {
      "title": "Makanan & Minuman",
      "count": 1
    }
  ],
  "reviewsTags": [],
  "gasPrices": [],
  "url": "https://www.google.com/maps/search/?api=1&query=PERISAI%20BPJS%20KETENAGAKERJAAN&query_place_id=ChIJUWvBUVEDQi4RtPkgdrxFDJY",
  "searchPageUrl": "https://www.google.com/maps/search/Perisai%20BPJS%20ketenagakerjaan?hl=id",
  "searchString": "Perisai BPJS ketenagakerjaan",
  "language": "id",
  "rank": 1,
  "isAdvertisement": false,
  "imageUrl": "https://lh3.googleusercontent.com/gps-cs-s/AHRPTWkSId_cZ0GriwiFg8LYtDLElhR0r2ao6LlA3xcwzybzhwDCG0hqEDgAYvRLsiVQH5Wc4BG52c_f_gPKQMd2U0Em9RpBX-5ZG58FwEI_qe40A8nzFBBoy2MoqlWgrvPn_fg68_w1=w408-h306-k-no",
  "kgmid": "/g/11vb6hgs19",
  "questionsAndAnswers": [],
  "webResults": [],
  "tableReservationLinks": [],
  "tableReservationProviders": [],
  "bookingLinks": [],
  "restaurantData": {
    "tableReservationProvider": null
  },
  "ownerUpdates": [],
  "imageUrls": [],
  "reviews": [
    {
      "reviewerId": "111575105697903574759",
      "reviewerUrl": "https://www.google.com/maps/contrib/111575105697903574759?hl=id",
      "name": "Rizka Motor",
      "reviewerNumberOfReviews": 12,
      "isLocalGuide": true,
      "reviewerPhotoUrl": "https://lh3.googleusercontent.com/a-/ALV-UjUjZEzaMX5XmYVmdHPwHjkYCl0h4xInJqQci8s1da4fnazsPrk=s1920-c-rp-mo-ba12-br100",
      "text": "minta nomr wa nya dong yg bisa di hubungi",
      "textTranslated": null,
      "publishAt": "3 bulan lalu",
      "publishedAtDate": "2026-03-31T11:28:24.113Z",
      "likesCount": 0,
      "reviewId": "Ci9DQUlRQUNvZENodHljRjlvT2tkeGRrUmFkWFZUTkZCRU1rUnZWWHBTVVhkU2VtYxAB",
      "reviewUrl": "https://www.google.com/maps/reviews/data=!4m8!14m7!1m6!2m5!1sCi9DQUlRQUNvZENodHljRjlvT2tkeGRrUmFkWFZUTkZCRU1rUnZWWHBTVVhkU2VtYxAB!2m1!1s0x0:0x960c45bc7620f9b4!3m1!1s2@1:CAIQACodChtycF9oOkdxdkRadXVTNFBEMkRvVXpSUXdSemc%7C%7C?hl=id",
      "reviewOrigin": "Google",
      "stars": 4,
      "rating": null,
      "responseFromOwnerDate": null,
      "responseFromOwnerText": null,
      "reviewImageUrls": [],
      "reviewContext": {},
      "reviewDetailedRating": {},
      "visitedIn": null,
      "originalLanguage": "id",
      "translatedLanguage": null
    },
    {
      "reviewerId": "107377417336497676304",
      "reviewerUrl": "https://www.google.com/maps/contrib/107377417336497676304?hl=id",
      "name": "Mts_ Assyahiriyah",
      "reviewerNumberOfReviews": 1,
      "isLocalGuide": false,
      "reviewerPhotoUrl": "https://lh3.googleusercontent.com/a-/ALV-UjUwhnuiRltLz-DTPvsvKb6rRVoLcH39rxb2QhkdSaItwMvkIDE5=s1920-c-rp-mo-br100",
      "text": "mantappppp",
      "textTranslated": null,
      "publishAt": "2 tahun lalu",
      "publishedAtDate": "2023-09-24T09:51:47.149Z",
      "likesCount": 1,
      "reviewId": "ChdDSUhNMG9nS0VJQ0FnSURaLUt2V3dRRRAB",
      "reviewUrl": "https://www.google.com/maps/reviews/data=!4m8!14m7!1m6!2m5!1sChdDSUhNMG9nS0VJQ0FnSURaLUt2V3dRRRAB!2m1!1s0x0:0x960c45bc7620f9b4!3m1!1s2@1:CIHM0ogKEICAgIDZ-KvWwQE%7C%7C?hl=id",
      "reviewOrigin": "Google",
      "stars": 5,
      "rating": null,
      "responseFromOwnerDate": null,
      "responseFromOwnerText": null,
      "reviewImageUrls": [],
      "reviewContext": {},
      "reviewDetailedRating": {},
      "visitedIn": null,
      "originalLanguage": "id",
      "translatedLanguage": null
    },
    {
      "reviewerId": "100802097111276280712",
      "reviewerUrl": "https://www.google.com/maps/contrib/100802097111276280712?hl=id",
      "name": "Mifassa cikande",
      "reviewerNumberOfReviews": 1,
      "isLocalGuide": false,
      "reviewerPhotoUrl": "https://lh3.googleusercontent.com/a-/ALV-UjXzoU-mgNrhjH7TdeiG8U2UGhf-1QkrgMEkubC-1HOxtmYPQ70L=s1920-c-rp-mo-br100",
      "text": "lanjutkan anak muda",
      "textTranslated": null,
      "publishAt": "2 tahun lalu",
      "publishedAtDate": "2023-09-24T09:50:57.786Z",
      "likesCount": 1,
      "reviewId": "ChdDSUhNMG9nS0VJQ0FnSURaLU11UHB3RRAB",
      "reviewUrl": "https://www.google.com/maps/reviews/data=!4m8!14m7!1m6!2m5!1sChdDSUhNMG9nS0VJQ0FnSURaLU11UHB3RRAB!2m1!1s0x0:0x960c45bc7620f9b4!3m1!1s2@1:CIHM0ogKEICAgIDZ-MuPpwE%7C%7C?hl=id",
      "reviewOrigin": "Google",
      "stars": 5,
      "rating": null,
      "responseFromOwnerDate": null,
      "responseFromOwnerText": null,
      "reviewImageUrls": [],
      "reviewContext": {},
      "reviewDetailedRating": {},
      "visitedIn": null,
      "originalLanguage": "id",
      "translatedLanguage": null
    },
    {
      "reviewerId": "113618304829893109499",
      "reviewerUrl": "https://www.google.com/maps/contrib/113618304829893109499?hl=id",
      "name": "Hayat Ruhiyat",
      "reviewerNumberOfReviews": 2,
      "isLocalGuide": false,
      "reviewerPhotoUrl": "https://lh3.googleusercontent.com/a-/ALV-UjUFxkHADNVFw2DlCMp6jcN5OltqltpY_bqsS9TY2XESCIGpCr06=s1920-c-rp-mo-br100",
      "text": "(y)",
      "textTranslated": null,
      "publishAt": "2 tahun lalu",
      "publishedAtDate": "2023-09-24T09:49:00.029Z",
      "likesCount": 1,
      "reviewId": "ChdDSUhNMG9nS0VJQ0FnSURaLUl2SHdBRRAB",
      "reviewUrl": "https://www.google.com/maps/reviews/data=!4m8!14m7!1m6!2m5!1sChdDSUhNMG9nS0VJQ0FnSURaLUl2SHdBRRAB!2m1!1s0x0:0x960c45bc7620f9b4!3m1!1s2@1:CIHM0ogKEICAgIDZ-IvHwAE%7C%7C?hl=id",
      "reviewOrigin": "Google",
      "stars": 5,
      "rating": null,
      "responseFromOwnerDate": null,
      "responseFromOwnerText": null,
      "reviewImageUrls": [],
      "reviewContext": {},
      "reviewDetailedRating": {},
      "visitedIn": null,
      "originalLanguage": "en",
      "translatedLanguage": null
    },
    {
      "reviewerId": "116944533352278624115",
      "reviewerUrl": "https://www.google.com/maps/contrib/116944533352278624115?hl=id",
      "name": "Nurhadi Dedi",
      "reviewerNumberOfReviews": 1,
      "isLocalGuide": false,
      "reviewerPhotoUrl": "https://lh3.googleusercontent.com/a/ACg8ocKenSTnc-BSTPmuTMBC3HpCZHZ0PdbMz2MNyTeTXQUp81y5Aw=s1920-c-rp-mo-br100",
      "text": "Jempollll",
      "textTranslated": null,
      "publishAt": "2 tahun lalu",
      "publishedAtDate": "2023-09-22T17:39:44.012Z",
      "likesCount": 1,
      "reviewId": "ChdDSUhNMG9nS0VJQ0FnSURac0p5Rm5RRRAB",
      "reviewUrl": "https://www.google.com/maps/reviews/data=!4m8!14m7!1m6!2m5!1sChdDSUhNMG9nS0VJQ0FnSURac0p5Rm5RRRAB!2m1!1s0x0:0x960c45bc7620f9b4!3m1!1s2@1:CIHM0ogKEICAgIDZsJyFnQE%7C%7C?hl=id",
      "reviewOrigin": "Google",
      "stars": 5,
      "rating": null,
      "responseFromOwnerDate": null,
      "responseFromOwnerText": null,
      "reviewImageUrls": [],
      "reviewContext": {},
      "reviewDetailedRating": {},
      "visitedIn": null,
      "originalLanguage": "id",
      "translatedLanguage": null
    },
    {
      "reviewerId": "108745689394461370586",
      "reviewerUrl": "https://www.google.com/maps/contrib/108745689394461370586?hl=id",
      "name": "auliya suriah",
      "reviewerNumberOfReviews": 2,
      "isLocalGuide": false,
      "reviewerPhotoUrl": "https://lh3.googleusercontent.com/a-/ALV-UjWhH1DS7gjPUK2r82bdS3PoiJdc3nKgfb7yi0z6i5BB9NYftENyEA=s1920-c-rp-mo-br100",
      "text": "Lakukan untuk kepedulian terhadap sesama.",
      "textTranslated": null,
      "publishAt": "2 tahun lalu",
      "publishedAtDate": "2023-09-10T18:18:26.188Z",
      "likesCount": 1,
      "reviewId": "ChZDSUhNMG9nS0VJQ0FnSUNacnBUdEZ3EAE",
      "reviewUrl": "https://www.google.com/maps/reviews/data=!4m8!14m7!1m6!2m5!1sChZDSUhNMG9nS0VJQ0FnSUNacnBUdEZ3EAE!2m1!1s0x0:0x960c45bc7620f9b4!3m1!1s2@1:CIHM0ogKEICAgICZrpTtFw%7C%7C?hl=id",
      "reviewOrigin": "Google",
      "stars": 5,
      "rating": null,
      "responseFromOwnerDate": null,
      "responseFromOwnerText": null,
      "reviewImageUrls": [],
      "reviewContext": {},
      "reviewDetailedRating": {},
      "visitedIn": null,
      "originalLanguage": "id",
      "translatedLanguage": null
    }
  ],
  "leadsEnrichment": [],
  "kategori": "Pelayanan Publik"
}