{
  "title": "Stadion Putra Raharja Fc Sidoraharjo",
  "subTitle": null,
  "description": null,
  "price": null,
  "categoryName": "Tempat Olahraga Anggar",
  "address": "MFFV+8QH, Jl. Dawarblandong - kedamean, Sumber Jambe, Sidoraharjo, Kec. Kedamean, Kabupaten Gresik, Jawa Timur 61175, Indonesia",
  "neighborhood": "Sumber Jambe, Sidoraharjo, Kecamatan Kedamean",
  "street": "MFFV+8QH, Jl. Dawarblandong - kedamean",
  "city": "Kabupaten Gresik",
  "postalCode": "61175",
  "state": "Jawa Timur",
  "countryCode": "ID",
  "phone": "",
  "phoneUnformatted": "",
  "claimThisBusiness": true,
  "location": {
    "lat": -7.3266786,
    "lng": 112.4944764
  },
  "locatedIn": null,
  "floor": null,
  "plusCode": null,
  "menu": null,
  "servicesLink": null,
  "totalScore": 4.9,
  "permanentlyClosed": false,
  "temporarilyClosed": false,
  "placeId": "ChIJNbmd-LQFeC4R0EY0h1sVLYw",
  "categories": [
    "Tempat Olahraga Anggar"
  ],
  "fid": "0x2e7805b4f89db935:0x8c2d155b873446d0",
  "cid": "10100753022116447952",
  "reviewsCount": 13,
  "imagesCount": 24,
  "imageCategories": [
    "Semua",
    "Street View & 360°",
    "Video"
  ],
  "scrapedAt": "2026-07-20T11:30:55.653Z",
  "reserveTableUrl": null,
  "googleFoodUrl": null,
  "hotelStars": null,
  "hotelDescription": null,
  "checkInDate": null,
  "checkOutDate": null,
  "hotelAds": [],
  "popularTimesLiveText": null,
  "popularTimesLivePercent": null,
  "popularTimesHistogram": {},
  "openingHours": [],
  "peopleAlsoSearch": [
    {
      "category": "Orang lain juga menelusuri",
      "title": "Lapangan Buduk Stadium",
      "reviewsCount": 0,
      "totalScore": 0
    },
    {
      "category": "Orang lain juga menelusuri",
      "title": "Stadion RIAZORE TURIREJO- KEDAMEAN",
      "reviewsCount": 1,
      "totalScore": 5
    },
    {
      "category": "Orang lain juga menelusuri",
      "title": "Stadion Sumberame",
      "reviewsCount": 4,
      "totalScore": 3
    },
    {
      "category": "Orang lain juga menelusuri",
      "title": "Lapangan Mojowuku FC",
      "reviewsCount": 1,
      "totalScore": 5
    },
    {
      "category": "Orang lain juga menelusuri",
      "title": "Lapangan Gelora Putra Punduttrate",
      "reviewsCount": 9,
      "totalScore": 4.9
    }
  ],
  "placesTags": [],
  "reviewsTags": [],
  "gasPrices": [],
  "url": "https://www.google.com/maps/search/?api=1&query=Stadion%20Putra%20Raharja%20Fc%20Sidoraharjo&query_place_id=ChIJNbmd-LQFeC4R0EY0h1sVLYw",
  "searchPageUrl": "https://www.google.com/maps/search/Stadion%20Sidoraharjo?hl=id",
  "searchString": "Stadion Sidoraharjo",
  "language": "id",
  "rank": 1,
  "isAdvertisement": false,
  "imageUrl": "https://lh3.googleusercontent.com/gps-cs-s/AHRPTWmUBGb2M6o3CqhDsvmFkHbiov2ZC_hmC7WL9dICI4fHGhcehLSH5y-TMp9U5uua3MeN8FekE3tXCT2kFLgiLc8dxoGL9ZFM1e9RBWuUkcyA3BY3fv594uFwng3Jk996ad_zxE7I=w408-h306-k-no",
  "kgmid": "/g/11kz20n03c",
  "reviewsDistribution": {
    "oneStar": 0,
    "twoStar": 0,
    "threeStar": 0,
    "fourStar": 1,
    "fiveStar": 12
  },
  "questionsAndAnswers": [],
  "webResults": [],
  "tableReservationLinks": [],
  "tableReservationProviders": [],
  "bookingLinks": [],
  "restaurantData": {
    "tableReservationProvider": null
  },
  "ownerUpdates": [],
  "imageUrls": [],
  "reviews": [
    {
      "reviewerId": "114714804090583949390",
      "reviewerUrl": "https://www.google.com/maps/contrib/114714804090583949390?hl=id",
      "name": "tofa Meinanto",
      "reviewerNumberOfReviews": 13,
      "isLocalGuide": true,
      "reviewerPhotoUrl": "https://lh3.googleusercontent.com/a/ACg8ocKrTJUnMporoV4Y8TtUju6uS9W2FkBgQPuQRzukA-CdNBcmuIw=s1920-c-rp-mo-ba12-br100",
      "text": null,
      "textTranslated": null,
      "publishAt": "6 bulan lalu",
      "publishedAtDate": "2026-01-16T12:41:56.873Z",
      "likesCount": 0,
      "reviewId": "Ci9DQUlRQUNvZENodHljRjlvT21Jd1ZrSlVUUzFFU0VOdU1rNXRUalpMWm10MGMwRRAB",
      "reviewUrl": "https://www.google.com/maps/reviews/data=!4m8!14m7!1m6!2m5!1sCi9DQUlRQUNvZENodHljRjlvT21Jd1ZrSlVUUzFFU0VOdU1rNXRUalpMWm10MGMwRRAB!2m1!1s0x0:0x8c2d155b873446d0!3m1!1s2@1:CAIQACodChtycF9oOmIwVkJUTS1ESENuMk5tTjZLZmt0c0E%7C%7C?hl=id",
      "reviewOrigin": "Google",
      "stars": 5,
      "rating": null,
      "responseFromOwnerDate": null,
      "responseFromOwnerText": null,
      "reviewImageUrls": [],
      "reviewContext": {},
      "reviewDetailedRating": {},
      "visitedIn": null,
      "originalLanguage": null,
      "translatedLanguage": null
    },
    {
      "reviewerId": "118344152323144159046",
      "reviewerUrl": "https://www.google.com/maps/contrib/118344152323144159046?hl=id",
      "name": "Cak har Har",
      "reviewerNumberOfReviews": 4,
      "isLocalGuide": false,
      "reviewerPhotoUrl": "https://lh3.googleusercontent.com/a/ACg8ocIuC_1J_kl3kJZRzU7SHdWtyUA7zHHsPUDtCe5k7QljSs7pMA=s1920-c-rp-mo-br100",
      "text": "Bagus , pas separing ke situ pemainnya sangat keras ,",
      "textTranslated": null,
      "publishAt": "10 bulan lalu",
      "publishedAtDate": "2025-08-27T04:32:22.787Z",
      "likesCount": 0,
      "reviewId": "Ci9DQUlRQUNvZENodHljRjlvT2xZdGVGZ3dkR0ZEVFZwWGIyVm9Ta05RWkhsWlRsRRAB",
      "reviewUrl": "https://www.google.com/maps/reviews/data=!4m8!14m7!1m6!2m5!1sCi9DQUlRQUNvZENodHljRjlvT2xZdGVGZ3dkR0ZEVFZwWGIyVm9Ta05RWkhsWlRsRRAB!2m1!1s0x0:0x8c2d155b873446d0!3m1!1s2@1:CAIQACodChtycF9oOlYteFgwdGFDTVpXb2VoSkNQZHlZTlE%7C%7C?hl=id",
      "reviewOrigin": "Google",
      "stars": 5,
      "rating": null,
      "responseFromOwnerDate": null,
      "responseFromOwnerText": null,
      "reviewImageUrls": [],
      "reviewContext": {},
      "reviewDetailedRating": {},
      "visitedIn": null,
      "originalLanguage": "id",
      "translatedLanguage": null
    },
    {
      "reviewerId": "100775473603106426335",
      "reviewerUrl": "https://www.google.com/maps/contrib/100775473603106426335?hl=id",
      "name": "Ahmad Fery Ramadhani",
      "reviewerNumberOfReviews": 7,
      "isLocalGuide": true,
      "reviewerPhotoUrl": "https://lh3.googleusercontent.com/a-/ALV-UjV9Wf-VlaNtFXDdLRh1Dw_yASkY1F88mjdMs7p5n3MyY5aLv58E=s1920-c-rp-mo-ba12-br100",
      "text": null,
      "textTranslated": null,
      "publishAt": "10 bulan lalu",
      "publishedAtDate": "2025-08-26T14:30:51.476Z",
      "likesCount": 0,
      "reviewId": "Ci9DQUlRQUNvZENodHljRjlvT2xKWVYwaFFURWcwYUVRMGNXbGFaV28wT0VSdFZWRRAB",
      "reviewUrl": "https://www.google.com/maps/reviews/data=!4m8!14m7!1m6!2m5!1sCi9DQUlRQUNvZENodHljRjlvT2xKWVYwaFFURWcwYUVRMGNXbGFaV28wT0VSdFZWRRAB!2m1!1s0x0:0x8c2d155b873446d0!3m1!1s2@1:CAIQACodChtycF9oOlJYV0hQTEg0aEQ0cWlaZWo0OERtVVE%7C%7C?hl=id",
      "reviewOrigin": "Google",
      "stars": 5,
      "rating": null,
      "responseFromOwnerDate": null,
      "responseFromOwnerText": null,
      "reviewImageUrls": [],
      "reviewContext": {},
      "reviewDetailedRating": {},
      "visitedIn": null,
      "originalLanguage": null,
      "translatedLanguage": null
    },
    {
      "reviewerId": "113146015927881968268",
      "reviewerUrl": "https://www.google.com/maps/contrib/113146015927881968268?hl=id",
      "name": "Ahmad Hafidun Nasyir",
      "reviewerNumberOfReviews": 0,
      "isLocalGuide": false,
      "reviewerPhotoUrl": "https://lh3.googleusercontent.com/a-/ALV-UjWuLTkaAE_nR8xkcY1smmPfb6IbbN-ciP-3PUirVdZgTK9wWsJL=s1920-c-rp-mo-br100",
      "text": null,
      "textTranslated": null,
      "publishAt": "setahun lalu",
      "publishedAtDate": "2025-02-26T10:46:42.287Z",
      "likesCount": 0,
      "reviewId": "ChZDSUhNMG9nS0VJQ0FnTURnOWVqV1VBEAE",
      "reviewUrl": "https://www.google.com/maps/reviews/data=!4m8!14m7!1m6!2m5!1sChZDSUhNMG9nS0VJQ0FnTURnOWVqV1VBEAE!2m1!1s0x0:0x8c2d155b873446d0!3m1!1s2@1:CIHM0ogKEICAgMDg9ejWUA%7C%7C?hl=id",
      "reviewOrigin": "Google",
      "stars": 5,
      "rating": null,
      "responseFromOwnerDate": null,
      "responseFromOwnerText": null,
      "reviewImageUrls": [],
      "reviewContext": {},
      "reviewDetailedRating": {},
      "visitedIn": null,
      "originalLanguage": null,
      "translatedLanguage": null
    },
    {
      "reviewerId": "102035059930718358859",
      "reviewerUrl": "https://www.google.com/maps/contrib/102035059930718358859?hl=id",
      "name": "Bang Sho'im",
      "reviewerNumberOfReviews": 0,
      "isLocalGuide": false,
      "reviewerPhotoUrl": "https://lh3.googleusercontent.com/a/ACg8ocL1RGe-SgQVSkG9EsiqroPPNu2oFZn7WGUpUqWgnQ-4g2Fg3Q=s1920-c-rp-mo-br100",
      "text": null,
      "textTranslated": null,
      "publishAt": "setahun lalu",
      "publishedAtDate": "2024-07-25T23:49:31.941Z",
      "likesCount": 0,
      "reviewId": "ChdDSUhNMG9nS0VJQ0FnSUNibXRpanRnRRAB",
      "reviewUrl": "https://www.google.com/maps/reviews/data=!4m8!14m7!1m6!2m5!1sChdDSUhNMG9nS0VJQ0FnSUNibXRpanRnRRAB!2m1!1s0x0:0x8c2d155b873446d0!3m1!1s2@1:CIHM0ogKEICAgICbmtijtgE%7C%7C?hl=id",
      "reviewOrigin": "Google",
      "stars": 5,
      "rating": null,
      "responseFromOwnerDate": null,
      "responseFromOwnerText": null,
      "reviewImageUrls": [],
      "reviewContext": {},
      "reviewDetailedRating": {},
      "visitedIn": null,
      "originalLanguage": null,
      "translatedLanguage": null
    },
    {
      "reviewerId": "112134909440373189632",
      "reviewerUrl": "https://www.google.com/maps/contrib/112134909440373189632?hl=id",
      "name": "Ferynt Sby",
      "reviewerNumberOfReviews": 381,
      "isLocalGuide": true,
      "reviewerPhotoUrl": "https://lh3.googleusercontent.com/a-/ALV-UjWB6WtXMCmWHxUhhlrQvtCWkurCDurKI6Wt2XvGpUWMDmNOk6Y=s1920-c-rp-mo-ba12-br100",
      "text": "Lapangan bola yg bagus,perlu perawatan n perbaikan sarana di sekitarnya",
      "textTranslated": null,
      "publishAt": "2 tahun lalu",
      "publishedAtDate": "2024-05-19T11:34:04.857Z",
      "likesCount": 2,
      "reviewId": "ChdDSUhNMG9nS0VJQ0FnSUNUbV96MW9nRRAB",
      "reviewUrl": "https://www.google.com/maps/reviews/data=!4m8!14m7!1m6!2m5!1sChdDSUhNMG9nS0VJQ0FnSUNUbV96MW9nRRAB!2m1!1s0x0:0x8c2d155b873446d0!3m1!1s2@1:CIHM0ogKEICAgICTm_z1ogE%7C%7C?hl=id",
      "reviewOrigin": "Google",
      "stars": 4,
      "rating": null,
      "responseFromOwnerDate": null,
      "responseFromOwnerText": null,
      "reviewImageUrls": [],
      "reviewContext": {},
      "reviewDetailedRating": {},
      "visitedIn": null,
      "originalLanguage": "id",
      "translatedLanguage": null
    },
    {
      "reviewerId": "108692393440348086966",
      "reviewerUrl": "https://www.google.com/maps/contrib/108692393440348086966?hl=id",
      "name": "Agung Akhmad",
      "reviewerNumberOfReviews": 2,
      "isLocalGuide": false,
      "reviewerPhotoUrl": "https://lh3.googleusercontent.com/a-/ALV-UjW_vFQpi2F5hhVmnd5gcjP_UZs6s0kGZXhP5cz-54wLLxlNB7Q=s1920-c-rp-mo-br100",
      "text": null,
      "textTranslated": null,
      "publishAt": "3 tahun lalu",
      "publishedAtDate": "2023-04-07T01:11:43.279Z",
      "likesCount": 0,
      "reviewId": "ChdDSUhNMG9nS0VJQ0FnSUNSbFptdzBRRRAB",
      "reviewUrl": "https://www.google.com/maps/reviews/data=!4m8!14m7!1m6!2m5!1sChdDSUhNMG9nS0VJQ0FnSUNSbFptdzBRRRAB!2m1!1s0x0:0x8c2d155b873446d0!3m1!1s2@1:CIHM0ogKEICAgICRlZmw0QE%7C%7C?hl=id",
      "reviewOrigin": "Google",
      "stars": 5,
      "rating": null,
      "responseFromOwnerDate": null,
      "responseFromOwnerText": null,
      "reviewImageUrls": [],
      "reviewContext": {},
      "reviewDetailedRating": {},
      "visitedIn": null,
      "originalLanguage": null,
      "translatedLanguage": null
    },
    {
      "reviewerId": "117647057026273898634",
      "reviewerUrl": "https://www.google.com/maps/contrib/117647057026273898634?hl=id",
      "name": "D Permana",
      "reviewerNumberOfReviews": 8,
      "isLocalGuide": true,
      "reviewerPhotoUrl": "https://lh3.googleusercontent.com/a/ACg8ocLgevNh7a8nl1jljFXoUtoRxe-oyG8z-S7vml-7aJ3uP0jZDpIm=s1920-c-rp-mo-ba12-br100",
      "text": null,
      "textTranslated": null,
      "publishAt": "3 tahun lalu",
      "publishedAtDate": "2023-01-27T04:21:18.169Z",
      "likesCount": 0,
      "reviewId": "ChZDSUhNMG9nS0VJQ0FnSURCZy02VUFREAE",
      "reviewUrl": "https://www.google.com/maps/reviews/data=!4m8!14m7!1m6!2m5!1sChZDSUhNMG9nS0VJQ0FnSURCZy02VUFREAE!2m1!1s0x0:0x8c2d155b873446d0!3m1!1s2@1:CIHM0ogKEICAgIDBg-6UAQ%7C%7C?hl=id",
      "reviewOrigin": "Google",
      "stars": 5,
      "rating": null,
      "responseFromOwnerDate": null,
      "responseFromOwnerText": null,
      "reviewImageUrls": [],
      "reviewContext": {},
      "reviewDetailedRating": {},
      "visitedIn": null,
      "originalLanguage": null,
      "translatedLanguage": null
    },
    {
      "reviewerId": "105703051779281023604",
      "reviewerUrl": "https://www.google.com/maps/contrib/105703051779281023604?hl=id",
      "name": "Alfuad Muhammad",
      "reviewerNumberOfReviews": 0,
      "isLocalGuide": false,
      "reviewerPhotoUrl": "https://lh3.googleusercontent.com/a-/ALV-UjW3LdMo2tOoicZ2nlIMPuI5UnO5AHgOFXTAufMRcV6uE6BxC5oC=s1920-c-rp-mo-br100",
      "text": null,
      "textTranslated": null,
      "publishAt": "4 tahun lalu",
      "publishedAtDate": "2022-01-23T11:36:05.186Z",
      "likesCount": 0,
      "reviewId": "ChZDSUhNMG9nS0VJQ0FnSURtNHNLQ0xBEAE",
      "reviewUrl": "https://www.google.com/maps/reviews/data=!4m8!14m7!1m6!2m5!1sChZDSUhNMG9nS0VJQ0FnSURtNHNLQ0xBEAE!2m1!1s0x0:0x8c2d155b873446d0!3m1!1s2@1:CIHM0ogKEICAgIDm4sKCLA%7C%7C?hl=id",
      "reviewOrigin": "Google",
      "stars": 5,
      "rating": null,
      "responseFromOwnerDate": null,
      "responseFromOwnerText": null,
      "reviewImageUrls": [],
      "reviewContext": {},
      "reviewDetailedRating": {},
      "visitedIn": null,
      "originalLanguage": null,
      "translatedLanguage": null
    },
    {
      "reviewerId": "108610529668153111446",
      "reviewerUrl": "https://www.google.com/maps/contrib/108610529668153111446?hl=id",
      "name": "Muhammad Zain",
      "reviewerNumberOfReviews": 16,
      "isLocalGuide": true,
      "reviewerPhotoUrl": "https://lh3.googleusercontent.com/a/ACg8ocLFjkVznbhkT63v1g4SAm74r1m_qU5jQvw6P9iyb4UDR5saeQ=s1920-c-rp-mo-ba12-br100",
      "text": "Lapangan standar nasional",
      "textTranslated": null,
      "publishAt": "4 tahun lalu",
      "publishedAtDate": "2021-08-05T04:24:49.209Z",
      "likesCount": 0,
      "reviewId": "ChdDSUhNMG9nS0VJQ0FnSUNhcFp2aDJnRRAB",
      "reviewUrl": "https://www.google.com/maps/reviews/data=!4m8!14m7!1m6!2m5!1sChdDSUhNMG9nS0VJQ0FnSUNhcFp2aDJnRRAB!2m1!1s0x0:0x8c2d155b873446d0!3m1!1s2@1:CIHM0ogKEICAgICapZvh2gE%7C%7C?hl=id",
      "reviewOrigin": "Google",
      "stars": 5,
      "rating": null,
      "responseFromOwnerDate": null,
      "responseFromOwnerText": null,
      "reviewImageUrls": [
        "https://lh3.googleusercontent.com/grass-cs/ACvplmPgn-QvtlWjCID28t6y5HL3A_GwSW0cwhipSJq4uEyuSXu2UTuTJ53P-iW8ZFbxIlMQtyUvfuZlpvV7gQKCFgsEzCyFK52r2tiMOXI_tUcCNi6cKkKfOvVhTjCeBUMl-JVeGclp=k-no"
      ],
      "reviewContext": {},
      "reviewDetailedRating": {},
      "visitedIn": null,
      "originalLanguage": "id",
      "translatedLanguage": null
    },
    {
      "reviewerId": "115045083591693933698",
      "reviewerUrl": "https://www.google.com/maps/contrib/115045083591693933698?hl=id",
      "name": "fajar jr",
      "reviewerNumberOfReviews": 3,
      "isLocalGuide": false,
      "reviewerPhotoUrl": "https://lh3.googleusercontent.com/a-/ALV-UjUTSei_SCPlk8j_AnzLNikAYgtZq4qQJjTBktMQiL6sDlR9T1Ek=s1920-c-rp-mo-br100",
      "text": null,
      "textTranslated": null,
      "publishAt": "5 tahun lalu",
      "publishedAtDate": "2021-03-20T11:09:48.743Z",
      "likesCount": 0,
      "reviewId": "ChdDSUhNMG9nS0VJQ0FnSUR5NTYzWHFRRRAB",
      "reviewUrl": "https://www.google.com/maps/reviews/data=!4m8!14m7!1m6!2m5!1sChdDSUhNMG9nS0VJQ0FnSUR5NTYzWHFRRRAB!2m1!1s0x0:0x8c2d155b873446d0!3m1!1s2@1:CIHM0ogKEICAgIDy563XqQE%7C%7C?hl=id",
      "reviewOrigin": "Google",
      "stars": 5,
      "rating": null,
      "responseFromOwnerDate": null,
      "responseFromOwnerText": null,
      "reviewImageUrls": [
        "https://lh3.googleusercontent.com/grass-cs/ACvplmOTE4HCAlRwgWp1MSqo56IsU4LF8YzbesHNdb_sgsD94tI_6E3ZOUBxhi_bh6AKtTmZRKPmK78qh-JpdO7NUkgmuOJzvRdx6Pnnobl2KONsTJkDiurqMhY5upV5zXthQkFHWwDilQ=k-no",
        "https://lh3.googleusercontent.com/grass-cs/ACvplmPdYxQE8O4L_xttOyBK4FIgYQFAxavKdCPTNjcawQU81hE7xOfRH7w4hqFTNvk3RpeJNVnIMDCv_SBtmAxdm5hEMV0ZrTD1CXv7W_zmqNeUrHk_8PeM-oNIO0TnzA5kE0QjtsEj=k-no",
        "https://lh3.googleusercontent.com/grass-cs/ACvplmMpH_yjFh38c_o4zp1S19niAnW8YmypTbR4IouTw8I1RlicjJ326e_m1t1dGkoJNDrLvVBW9KlWQTk7tYPpHWlfCgIJRl8bYzhrD0ihCklHyDWP3zUJ5nNoPewNmT-L-HvNLFtK=k-no"
      ],
      "reviewContext": {},
      "reviewDetailedRating": {},
      "visitedIn": null,
      "originalLanguage": null,
      "translatedLanguage": null
    },
    {
      "reviewerId": "112869831263792106273",
      "reviewerUrl": "https://www.google.com/maps/contrib/112869831263792106273?hl=id",
      "name": "AHMAD ARFIYANSYAH WIBOWO",
      "reviewerNumberOfReviews": 4,
      "isLocalGuide": false,
      "reviewerPhotoUrl": "https://lh3.googleusercontent.com/a-/ALV-UjVPs9Jp4oklRYXLgKwWb9FbJdn04J_yx8LhlD6nXW6H1xkRgU5IAg=s1920-c-rp-mo-br100",
      "text": "Joss",
      "textTranslated": null,
      "publishAt": "5 tahun lalu",
      "publishedAtDate": "2020-09-03T15:20:21.752Z",
      "likesCount": 2,
      "reviewId": "ChdDSUhNMG9nS0VJQ0FnSUNDeTVuaWhRRRAB",
      "reviewUrl": "https://www.google.com/maps/reviews/data=!4m8!14m7!1m6!2m5!1sChdDSUhNMG9nS0VJQ0FnSUNDeTVuaWhRRRAB!2m1!1s0x0:0x8c2d155b873446d0!3m1!1s2@1:CIHM0ogKEICAgICCy5nihQE%7C%7C?hl=id",
      "reviewOrigin": "Google",
      "stars": 5,
      "rating": null,
      "responseFromOwnerDate": null,
      "responseFromOwnerText": null,
      "reviewImageUrls": [],
      "reviewContext": {},
      "reviewDetailedRating": {},
      "visitedIn": null,
      "originalLanguage": "id",
      "translatedLanguage": null
    },
    {
      "reviewerId": "104429817922368625204",
      "reviewerUrl": "https://www.google.com/maps/contrib/104429817922368625204?hl=id",
      "name": "ALFA AL-FATIH",
      "reviewerNumberOfReviews": 4,
      "isLocalGuide": false,
      "reviewerPhotoUrl": "https://lh3.googleusercontent.com/a-/ALV-UjW5UoPard-seKcYpKcSRwLJuHxbW9fbMLMYRnmZCd1gD88YAlaq=s1920-c-rp-mo-br100",
      "text": null,
      "textTranslated": null,
      "publishAt": "5 tahun lalu",
      "publishedAtDate": "2020-09-01T07:02:40.868Z",
      "likesCount": 0,
      "reviewId": "ChZDSUhNMG9nS0VJQ0FnSUNDX2V6NGNnEAE",
      "reviewUrl": "https://www.google.com/maps/reviews/data=!4m8!14m7!1m6!2m5!1sChZDSUhNMG9nS0VJQ0FnSUNDX2V6NGNnEAE!2m1!1s0x0:0x8c2d155b873446d0!3m1!1s2@1:CIHM0ogKEICAgICC_ez4cg%7C%7C?hl=id",
      "reviewOrigin": "Google",
      "stars": 5,
      "rating": null,
      "responseFromOwnerDate": null,
      "responseFromOwnerText": null,
      "reviewImageUrls": [
        "https://lh3.googleusercontent.com/grass-cs/ACvplmOVkb9CdfEO0_bvvRRArj_3OdtbW0wYOvz_47TP7c9mhyfSqFVsyWkvnfz9sC7Eth1sSxyiGvghOr4BdgJR41XxCytQ6PXxm-xaSSoC86TdU6U0EQz1GTL6dj9pUTV2PAAfL9Qv=k-no"
      ],
      "reviewContext": {},
      "reviewDetailedRating": {},
      "visitedIn": null,
      "originalLanguage": null,
      "translatedLanguage": null
    }
  ],
  "leadsEnrichment": [],
  "kategori": "Olahraga"
}